sphinx_md_theme/__init__.py
sphinx_md_theme/templates/material_design/breadcrumbs.html
sphinx_md_theme/templates/material_design/footer.html
sphinx_md_theme/templates/material_design/header.html
sphinx_md_theme/templates/material_design/layout.html
sphinx_md_theme/templates/material_design/search.html
sphinx_md_theme/templates/material_design/searchbox.html
sphinx_md_theme/templates/material_design/theme.conf
sphinx_md_theme/templates/material_design/versions.html
sphinx_md_theme/templates/material_design/static/css/badge_only.css
sphinx_md_theme/templates/material_design/static/css/badge_only.css.map
sphinx_md_theme/templates/material_design/static/css/theme.css
sphinx_md_theme/templates/material_design/static/css/theme.css.map
sphinx_md_theme/templates/material_design/static/css/pygments/algol.css
sphinx_md_theme/templates/material_design/static/css/pygments/algol_nu.css
sphinx_md_theme/templates/material_design/static/css/pygments/autumn.css
sphinx_md_theme/templates/material_design/static/css/pygments/borland.css
sphinx_md_theme/templates/material_design/static/css/pygments/bw.css
sphinx_md_theme/templates/material_design/static/css/pygments/colorful.css
sphinx_md_theme/templates/material_design/static/css/pygments/default.css
sphinx_md_theme/templates/material_design/static/css/pygments/emacs.css
sphinx_md_theme/templates/material_design/static/css/pygments/friendly.css
sphinx_md_theme/templates/material_design/static/css/pygments/fruity.css
sphinx_md_theme/templates/material_design/static/css/pygments/igor.css
sphinx_md_theme/templates/material_design/static/css/pygments/lovelace.css
sphinx_md_theme/templates/material_design/static/css/pygments/manni.css
sphinx_md_theme/templates/material_design/static/css/pygments/monokai.css
sphinx_md_theme/templates/material_design/static/css/pygments/murphy.css
sphinx_md_theme/templates/material_design/static/css/pygments/native.css
sphinx_md_theme-0.1a4.dist-info/DESCRIPTION.rst
sphinx_md_theme-0.1a4.dist-info/METADATA
sphinx_md_theme-0.1a4.dist-info/RECORD
sphinx_md_theme-0.1a4.dist-info/WHEEL
sphinx_md_theme-0.1a4.dist-info/entry_points.txt
sphinx_md_theme-0.1a4.dist-info/metadata.json
sphinx_md_theme-0.1a4.dist-info/top_level.txt
