Metadata-Version: 2.0
Name: sphinx-md-theme
Version: 0.1a4
Summary: A Material design theme for Sphinx.
Home-page: https://github.com/darvid/sphinx_md_theme
Author: David Gidwani
Author-email: david.gidwani@gmail.com
License: MIT
Platform: UNKNOWN
Classifier: Development Status :: 3 - Alpha
Classifier: License :: OSI Approved :: BSD License
Classifier: Environment :: Console
Classifier: Environment :: Web Environment
Classifier: Intended Audience :: Developers
Classifier: Programming Language :: Python :: 2.7
Classifier: Programming Language :: Python :: 3
Classifier: Operating System :: OS Independent
Classifier: Topic :: Documentation
Classifier: Topic :: Software Development :: Documentation
